pcdr/__init__.py
pcdr/flow.py
pcdr/_internal/__init__.py
pcdr/_internal/basictermplot.py
pcdr/_internal/fileio.py
pcdr/_internal/flow_impl.py
pcdr/_internal/misc.py
pcdr/_internal/our_GR_blocks.py
pcdr/_internal/queue_to_guisink_flowgraph.py
pcdr/_internal/queue_to_waterfall_flowgraph.py
pcdr/_internal/types_and_contracts.py
pcdr/_internal/vector_to_guisink_flowgraph.py
pcdr/_internal/vector_tx_flowgraphs.py
pcdr/_internal/wavegen.py
pcdr/_internal/wrapped_GR_blocks.py
pcdr/_internal/_queue/__init__.py
pcdr/_internal/_queue/sink.py
pcdr/_internal/_queue/source.py
pcdr/unstable/__init__.py
pcdr/unstable/flow.py
pcdr/unstable/gnuradio_receiver.py
pcdr/unstable/gnuradio_sendlike.py
pcdr/unstable/misc.py
pcdr/unstable/misc2.py
pcdr/unstable/osmocom_queued_rx_flowgraph.py
pcdr/unstable/osmocom_queued_tx_flowgraph.py
pcdr/v0_compat/__init__.py
pcdr/v0_compat/basictermplot.py
pcdr/v0_compat/gnuradio_sender.py
pcdr/v0_compat/helpers.py
pcdr/v0_compat/modulators.py
pcdr/v0_compat/wavegen.py
pcdr-1.0.1.dist-info/LICENSE
pcdr-1.0.1.dist-info/METADATA
pcdr-1.0.1.dist-info/WHEEL
pcdr-1.0.1.dist-info/top_level.txt
pcdr-1.0.1.dist-info/RECORD
