Metadata-Version: 2.1
Name: pcdr
Version: 1.0.1
Summary: GNU Radio-based transmit and receive wrappers and more
Author: james-pcdr
Project-URL: Homepage, https://github.com/python-can-define-radio/pcdr
Project-URL: Bug Tracker, https://github.com/python-can-define-radio/pcdr/issues
Classifier: Programming Language :: Python :: 3
Classifier: Operating System :: OS Independent
Requires-Python: >=3.8
License-File: LICENSE
Requires-Dist: numpy <2.0,>=1.21
Requires-Dist: typeguard <5.0.0,>=3.0.0
Requires-Dist: attrs <=23.1.0,>=21.3.0
